Metadata-Version: 2.4
Name: llm-fragments-site-text
Version: 0.1
Summary: Run URLs through the Trafilatura to get plain text
Author: Dan Turkel, Simon Willison
License-Expression: Apache-2.0
Project-URL: Homepage, https://github.com/daturkel/llm-fragments-site-text
Project-URL: Changelog, https://github.com/daturkel/llm-fragments-site-text/releases
Project-URL: Issues, https://github.com/daturkel/llm-fragments-site-text/issues
Project-URL: CI, https://github.com/daturkel/llm-fragments-site-text/actions
Requires-Python: >=3.9
License-File: LICENSE
Requires-Dist: llm
Requires-Dist: trafilatura>=2.0.0
Provides-Extra: test
Requires-Dist: pytest; extra == "test"
Requires-Dist: pytest-httpx; extra == "test"
Dynamic: license-file
